{
  "classes": {
    "container": "container_12",
    "id": "footer"
  },
  "nav": {
    "links": [
      { "label": "Home", "href": "/" },
      { "label": "About Us", "href": "/view/about_us" },
      { "label": "Services", "href": "/view/services" },
      { "label": "Free Estimate", "href": "/view/estimate" },
      { "label": "Billing", "href": "/view/billing" },
      { "label": "Contact Us", "href": "/view/contact_us" }
    ]
  },
  "contact": {
    "company": "ProScapes of Atlanta",
    "phone": "404-514-6254",
    "emailLabel": "contact@ProScapesOfAtlanta.com",
    "emailHref": "mailto:proscapesofatl.kw@gmail.com"
  },
  "scripts": {
    "banner": true,
    "intervalMs": 5000
  }
}
